fitparse/__init__.py
fitparse/base.py
fitparse/processors.py
fitparse/profile.py
fitparse/records.py
fitparse/utils.py
python_fitparse-2.0.5.dist-info/METADATA
python_fitparse-2.0.5.dist-info/WHEEL
python_fitparse-2.0.5.dist-info/entry_points.txt
python_fitparse-2.0.5.dist-info/licenses/LICENSE
python_fitparse-2.0.5.dist-info/RECORD
