Metadata-Version: 2.4
Name: python-fitparse
Version: 2.0.5
Summary: Python library to parse ANT/Garmin .FIT files
Project-URL: Homepage, https://www.github.com/nbr23/python-fitparse
Project-URL: Repository, https://www.github.com/nbr23/python-fitparse
Project-URL: Issues, https://github.com/nbr23/python-fitparse/issues
Author-email: David Cooper <dave@kupesoft.com>, nbr23 <max@23.tf>
License: MIT License
License-File: LICENSE
Keywords: ant,files,fit,garmin,parse
Classifier: Development Status :: 5 - Production/Stable
Classifier: Intended Audience :: Developers
Classifier: License :: OSI Approved :: MIT License
Classifier: Programming Language :: Python :: 3
Classifier: Programming Language :: Python :: 3.8
Classifier: Programming Language :: Python :: 3.9
Classifier: Programming Language :: Python :: 3.10
Classifier: Programming Language :: Python :: 3.11
Classifier: Programming Language :: Python :: 3.12
Classifier: Topic :: Software Development :: Libraries :: Python Modules
Requires-Python: >=3.8
Provides-Extra: generate
Requires-Dist: openpyxl==3.1.5; extra == 'generate'
Requires-Dist: requests; extra == 'generate'
